frida_uiopen/__init__.py
frida_uiopen/uiopen.py
frida_uiopen/uiopen_agent.js
frida_uiopen-1.0.1.dist-info/METADATA
frida_uiopen-1.0.1.dist-info/WHEEL
frida_uiopen-1.0.1.dist-info/entry_points.txt
frida_uiopen-1.0.1.dist-info/top_level.txt
frida_uiopen-1.0.1.dist-info/RECORD
