Metadata-Version: 2.1
Name: frida-uiopen
Version: 1.0.1
Summary: Invoke the openURL of iOS based on frida.
Home-page: https://github.com/Cuihaixu/frida-uiopen
Author: Summer
Author-email: cuihaixu@126.com
License: wxWindows Library Licence, Version 3.1
Keywords: frida uiopen debugger dynamic instrumentation inject javascript windows macos linux ios iphone ipad android qnx
Classifier: Development Status :: 5 - Production/Stable
Classifier: Environment :: Console
Classifier: Environment :: MacOS X
Classifier: Environment :: Win32 (MS Windows)
Classifier: Intended Audience :: Developers
Classifier: Intended Audience :: Science/Research
Classifier: License :: OSI Approved
Classifier: Natural Language :: English
Classifier: Operating System :: MacOS :: MacOS X
Classifier: Operating System :: Microsoft :: Windows
Classifier: Operating System :: POSIX :: Linux
Classifier: Programming Language :: Python :: 3
Classifier: Programming Language :: Python :: 3.7
Classifier: Programming Language :: Python :: 3.8
Classifier: Programming Language :: Python :: 3.9
Classifier: Programming Language :: Python :: 3.10
Classifier: Programming Language :: JavaScript
Classifier: Topic :: Software Development :: Debuggers
Classifier: Topic :: Software Development :: Libraries :: Python Modules
Requires-Dist: colorama <1.0.0,>=0.2.7
Requires-Dist: frida <17.0.0,>=16.0.9
Requires-Dist: prompt-toolkit <4.0.0,>=2.0.0
Requires-Dist: pygments <3.0.0,>=2.0.2
